irsx/__init__.py
irsx/_version.py
irsx/dir_utils.py
irsx/file_utils.py
irsx/filing.py
irsx/flatten_utils.py
irsx/irsx_cli.py
irsx/irsx_index_cli.py
irsx/keyerror_utils.py
irsx/local_settings-example.py
irsx/log_utils.py
irsx/object_ids.py
irsx/settings.py
irsx/sked_dict_reader.py
irsx/standardizer.py
irsx/text_format_utils.py
irsx/type_utils.py
irsx/xmlrunner.py
irsxml-0.2.14.dist-info/LICENSE
irsxml-0.2.14.dist-info/METADATA
irsxml-0.2.14.dist-info/WHEEL
irsxml-0.2.14.dist-info/entry_points.txt
irsxml-0.2.14.dist-info/top_level.txt
irsxml-0.2.14.dist-info/RECORD
